[
    {
        "name":"A",
        "data" : [ 
                    {
                        "name":"June", 
                        "weight":52,
                        "tooltip": "A"
                    },
                    {
                        "name":"July", 
                        "weight": 85,
                        "tooltip": "A"
                    },
                    {
                        "name":"Aug", 
                        "weight":52,
                        "tooltip": "A"
                    },
                    {
                        "name":"Sep", 
                        "weight": 85,
                        "tooltip": "A"
                    },
                    {
                        "name":"Oct",
                        "weight": 42,
                        "tooltip": "A"
                    },
                    {
                        "name":"Nov",
                        "weight": 100,
                        "tooltip": "A"
                    },       
                    {
                        "name":"Dec",
                        "weight": 90,
                        "tooltip": "A"
                    }       
        ],
        "color": "#A2F3CA"
    },
    {
        "name":"B",
        "data" : [ 
                    {
                        "name":"June", 
                        "weight":52,
                        "tooltip": "B"
                    },
                    {
                        "name":"July", 
                        "weight": 85,
                        "tooltip": "B"
                    },
                    {
          
                        "name":"Aug", 
                        "weight":62,
                        "tooltip": "B"
                    },
                    {
                        "name":"Sep", 
                        "weight": 65,
                        "tooltip": "B"
                    },
                    {
                        "name":"Oct",
                        "weight": 32,
                        "tooltip": "B"
                    },
                    {
                        "name":"Nov",
                        "weight": 90,
                        "tooltip": "B"
                    },
                    {
                        "name":"Dec",
                        "weight": 90,
                        "tooltip": "B"
                    }              
        ],
        "color": "#87E7FF"
    },
    {
        "name":"C",
        "data" : [
                    {
                        "name":"June", 
                        "weight":52,
                        "tooltip": "C"
                    },
                    {
                        "name":"July", 
                        "weight": 85,
                        "tooltip": "C"
                    },
                    {
                        "name":"Aug", 
                        "weight":32,
                        "tooltip": "C"
                    },
                    {
                        "name":"Sep", 
                        "weight": 75,
                        "tooltip": "C"
                    },
                    {
                        "name":"Oct",
                        "weight": 80,
                        "tooltip": "C"
                    },
                    {
                        "name":"Nov",
                        "weight": 100,
                        "tooltip": "C"
                    },
                    {
                        "name":"Dec",
                        "weight": 120,
                        "tooltip": "C"
                    }       

        ],
        "color": "#73CAFF"
    },
    {
        "name":"D",
        "data" : [ 
                    {
                        "name":"June", 
                        "weight":52,
                        "tooltip": "D"
                    },
                    {
                        "name":"July", 
                        "weight": 85,
                        "tooltip": "D"
                    },
                    {
                        "name":"Aug", 
                        "weight":32,
                        "tooltip": "D"
                    },
                    {
                        "name":"Sep", 
                        "weight": 75,
                        "tooltip": "D"
                    },
                    {
                        "name":"Oct",
                        "weight": 100,
                        "tooltip": "D"
                    },
                    {
                        "name":"Nov",
                        "weight": 110,
                        "tooltip": "D"
                    },
                    {
                        "name":"Dec",
                        "weight": 70,
                        "tooltip": "D"
                    }                     

        ],
        "color": "#CCBAF8"
    }    
]