[{"iso2":"AL_01","size":76,"color":"yellow","tooltip":"none","highlight":false,"highlight_color":"none"},{"iso2":"AL_09","size":65,"color":"grey","tooltip":"none","highlight":false,"highlight_color":"none"},{"iso2":"AL_02","size":97,"color":"orange","tooltip":"none","highlight":false,"highlight_color":"none"},{"iso2":"AL_03","size":2,"color":"yellow","tooltip":"none","highlight":false,"highlight_color":"none"},{"iso2":"AL_04","size":62,"color":"green","tooltip":"none","highlight":false,"highlight_color":"none"},{"iso2":"AL_05","size":55,"color":"blue","tooltip":"none","highlight":false,"highlight_color":"none"},{"iso2":"AL_06","size":67,"color":"green","tooltip":"none","highlight":false,"highlight_color":"none"},{"iso2":"AL_07","size":85,"color":"orange","tooltip":"none","highlight":true,"highlight_color":"red"},{"iso2":"AL_08","size":34,"color":"blue","tooltip":"none","highlight":false,"highlight_color":"none"},{"iso2":"AL_10","size":54,"color":"green","tooltip":"none","highlight":false,"highlight_color":"none"},{"iso2":"AL_11","size":51,"color":"yellow","tooltip":"none","highlight":false,"highlight_color":"none"},{"iso2":"AL_12","size":67,"color":"yellow","tooltip":"none","highlight":false,"highlight_color":"none"}]
