[{"iso2":"IN_GJ_AH","size":100,"color":"grey","tooltip":"none"},{"iso2":"IN_GJ_AM","size":78,"color":"yellow","tooltip":"none"},{"iso2":"IN_GJ_AN","size":44,"color":"green","tooltip":"none"},{"iso2":"IN_GJ_BK","size":55,"color":"yellow","tooltip":"none"},{"iso2":"IN_GJ_BR","size":8,"color":"blue","tooltip":"none"},{"iso2":"IN_GJ_BV","size":32,"color":"blue","tooltip":"none"},{"iso2":"IN_GJ_DA","size":36,"color":"green","tooltip":"none"},{"iso2":"IN_GJ_GA","size":31,"color":"green","tooltip":"none"},{"iso2":"IN_GJ_JA","size":31,"color":"grey","tooltip":"none"},{"iso2":"IN_GJ_JU","size":18,"color":"green","tooltip":"none"},{"iso2":"IN_GJ_KA","size":65,"color":"orange","tooltip":"none"},{"iso2":"IN_GJ_KH","size":65,"color":"yellow","tooltip":"none"},{"iso2":"IN_GJ_MA","size":90,"color":"blue","tooltip":"none"},{"iso2":"IN_GJ_NR","size":78,"color":"grey","tooltip":"none"},{"iso2":"IN_GJ_NV","size":5,"color":"blue","tooltip":"none"},{"iso2":"IN_GJ_PM","size":33,"color":"green","tooltip":"none"},{"iso2":"IN_GJ_PA","size":31,"color":"blue","tooltip":"none"},{"iso2":"IN_GJ_PO","size":78,"color":"blue","tooltip":"none"},{"iso2":"IN_GJ_RA","size":47,"color":"yellow","tooltip":"none"},{"iso2":"IN_GJ_SK","size":92,"color":"grey","tooltip":"none"},{"iso2":"IN_GJ_ST","size":98,"color":"orange","tooltip":"none"},{"iso2":"IN_GJ_SN","size":65,"color":"grey","tooltip":"none"},{"iso2":"IN_GJ_DG","size":13,"color":"grey","tooltip":"none"},{"iso2":"IN_GJ_VD","size":79,"color":"orange","tooltip":"none"},{"iso2":"IN_GJ_VL","size":52,"color":"blue","tooltip":"none"},{"iso2":"IN_GJ_TA","size":66,"color":"yellow","tooltip":"none"}]